streamlit_react_components/__init__.py
streamlit_react_components/styled_container.py
streamlit_react_components/tailwind.py
streamlit_react_components/themes.py
streamlit_react_components/_frontend/index.css
streamlit_react_components/_frontend/index.html
streamlit_react_components/_frontend/index.js
streamlit_react_components/common/__init__.py
streamlit_react_components/common/button_group.py
streamlit_react_components/common/chart_legend.py
streamlit_react_components/common/data_table.py
streamlit_react_components/common/metric_row.py
streamlit_react_components/common/panel.py
streamlit_react_components/common/plotly_chart.py
streamlit_react_components/common/section_header.py
streamlit_react_components/common/smart_chart.py
streamlit_react_components/common/stat_card.py
streamlit_react_components/common/step_indicator.py
streamlit_react_components/form/__init__.py
streamlit_react_components/form/checkbox_group.py
streamlit_react_components/form/form_date_slider.py
streamlit_react_components/form/form_select.py
streamlit_react_components/form/form_slider.py
streamlit_react_components/form/radio_group.py
streamlit_react_components-1.8.1.1.dist-info/METADATA
streamlit_react_components-1.8.1.1.dist-info/WHEEL
streamlit_react_components-1.8.1.1.dist-info/top_level.txt
streamlit_react_components-1.8.1.1.dist-info/RECORD
