Metadata-Version: 2.4
Name: streamlit-react-components
Version: 1.8.1.1
Summary: Reusable React-based Streamlit components with Tailwind CSS styling
License: MIT
Project-URL: Homepage, https://github.com/your-org/streamlit-react-components
Classifier: Development Status :: 3 - Alpha
Classifier: Intended Audience :: Developers
Classifier: License :: OSI Approved :: MIT License
Classifier: Programming Language :: Python :: 3
Classifier: Programming Language :: Python :: 3.8
Classifier: Programming Language :: Python :: 3.9
Classifier: Programming Language :: Python :: 3.10
Classifier: Programming Language :: Python :: 3.11
Classifier: Programming Language :: Python :: 3.12
Requires-Python: >=3.8
Requires-Dist: streamlit>=1.24.0
